easywebdav2/__init__.py
easywebdav2/__version__.py
easywebdav2/client.py
easywebdav2-1.3.0.dist-info/DESCRIPTION.rst
easywebdav2-1.3.0.dist-info/METADATA
easywebdav2-1.3.0.dist-info/RECORD
easywebdav2-1.3.0.dist-info/WHEEL
easywebdav2-1.3.0.dist-info/entry_points.txt
easywebdav2-1.3.0.dist-info/metadata.json
easywebdav2-1.3.0.dist-info/top_level.txt
